pixhist/__init__.py
pixhist/api.py
pixhist/generators.py
pixhist/histogram.py
pixhist/ranges.py
pixhist/rendering.py
pixhist-0.0.2.dist-info/LICENSE
pixhist-0.0.2.dist-info/METADATA
pixhist-0.0.2.dist-info/WHEEL
pixhist-0.0.2.dist-info/top_level.txt
pixhist-0.0.2.dist-info/RECORD
