Metadata-Version: 2.1
Name: pixhist
Version: 0.0.2
Summary: Pixel histograms.
Home-page: https://github.com/sradc/PixHist
Author: Sidney Radcliffe
Author-email: sidneyradcliffe@gmail.com
License: UNKNOWN
Platform: UNKNOWN
Classifier: Programming Language :: Python :: 3
Classifier: License :: OSI Approved :: MIT License
Classifier: Operating System :: OS Independent
Requires-Python: >=3.6
Requires-Dist: numpy
Requires-Dist: numba
Provides-Extra: pixhist.rendering
Requires-Dist: matplotlib ; extra == 'pixhist.rendering'
